CHANGES.txt
README.txt
bootstrap.py
buildout.cfg
setup.py
src/zope/__init__.py
src/zope.app.versioncontrol.egg-info/PKG-INFO
src/zope.app.versioncontrol.egg-info/SOURCES.txt
src/zope.app.versioncontrol.egg-info/dependency_links.txt
src/zope.app.versioncontrol.egg-info/namespace_packages.txt
src/zope.app.versioncontrol.egg-info/not-zip-safe
src/zope.app.versioncontrol.egg-info/requires.txt
src/zope.app.versioncontrol.egg-info/top_level.txt
src/zope/app/__init__.py
src/zope/app/versioncontrol/README.txt
src/zope/app/versioncontrol/__init__.py
src/zope/app/versioncontrol/configure.zcml
src/zope/app/versioncontrol/event.py
src/zope/app/versioncontrol/history.py
src/zope/app/versioncontrol/interfaces.py
src/zope/app/versioncontrol/issues.txt
src/zope/app/versioncontrol/nonversioned.py
src/zope/app/versioncontrol/repository.py
src/zope/app/versioncontrol/tests.py
src/zope/app/versioncontrol/utility.py
src/zope/app/versioncontrol/version.py